chaosansible/__init__.py
chaosansible/actions.py
chaosansible/probes.py
chaostoolkit_ansible-0.2.3.dist-info/LICENSE
chaostoolkit_ansible-0.2.3.dist-info/METADATA
chaostoolkit_ansible-0.2.3.dist-info/WHEEL
chaostoolkit_ansible-0.2.3.dist-info/top_level.txt
chaostoolkit_ansible-0.2.3.dist-info/RECORD
