Metadata-Version: 2.1
Name: chaostoolkit-ansible
Version: 0.2.3
Summary: Chaos toolkit Extension for using ansible as event execution tool
Home-page: http://chaostoolkit.org
Author: Mickael Roger
Author-email: mickael@mickael-roger.com
License: Apache License Version 2.0
Platform: UNKNOWN
Classifier: Development Status :: 2 - Pre-Alpha
Classifier: Intended Audience :: Developers
Classifier: License :: Freely Distributable
Classifier: Operating System :: OS Independent
Classifier: License :: OSI Approved :: Apache Software License
Classifier: Programming Language :: Python
Classifier: Programming Language :: Python :: 3
Classifier: Programming Language :: Python :: 3.5
Classifier: Programming Language :: Python :: 3.6
Classifier: Programming Language :: Python :: 3.7
Classifier: Programming Language :: Python :: 3.8
Classifier: Programming Language :: Python :: Implementation
Classifier: Programming Language :: Python :: Implementation :: CPython
Requires-Python: >=3.5.*
License-File: LICENSE
Requires-Dist: chaostoolkit (>=1.7.1)
Requires-Dist: chaostoolkit-lib (>=1.1.2)
Requires-Dist: chaostoolkit-lib[jsonpath]
Requires-Dist: logzero
Requires-Dist: ansible (<3.0,>=2.9.0)
Requires-Dist: jsonpath-ng
